[
  {
    "title": "不是这代人不识货，是没人教他们怎么识货。#荔枝菌 #传承 #老广智慧",
    "platform": "weixin",
    "publish_date": "2026-07-02",
    "plays_delta": 415,
    "likes_delta": 1,
    "comments_delta": 0,
    "shares_delta": 0,
    "followers_delta": 0
  },
  {
    "title": "越懂吃的人，越不敢给荔枝菌加料。#荔枝菌 #老广吃法 #质疑",
    "platform": "weixin",
    "publish_date": "2026-07-02",
    "plays_delta": 0,
    "likes_delta": 0,
    "comments_delta": 0,
    "shares_delta": 0,
    "followers_delta": 0
  },
  {
    "title": "不是所有野生菌都值得吃，有些只是\"野生\"两个字值钱。#荔枝菌 #质疑",
    "platform": "weixin",
    "publish_date": "2026-07-02",
    "plays_delta": 589,
    "likes_delta": 0,
    "comments_delta": 0,
    "shares_delta": 0,
    "followers_delta": 0
  },
  {
    "title": "买荔枝菌最怕不是贵，是开箱那一刻鲜味已经在路上塌了。#荔枝菌 #顺丰冷链 #滋元堂",
    "platform": "weixin",
    "publish_date": "2026-07-02",
    "plays_delta": 328,
    "likes_delta": 0,
    "comments_delta": 0,
    "shares_delta": 0,
    "followers_delta": 0
  },
  {
    "title": "幼儿园妈妈问荔枝菌怎么做，不是跟风，是孩子真的愿意多吃两口。#荔枝菌 #饭霸养成 #妈妈群",
    "platform": "weixin",
    "publish_date": "2026-07-02",
    "plays_delta": 169,
    "likes_delta": 0,
    "comments_delta": 0,
    "shares_delta": 0,
    "followers_delta": 0
  },
  {
    "title": "雨天采荔枝菌最难的不是淋湿，是要赶在它闷坏前把鲜味带回来。#荔枝菌 #雨天采菌 #源头溯源",
    "platform": "weixin",
    "publish_date": "2026-07-02",
    "plays_delta": 157,
    "likes_delta": 0,
    "comments_delta": 0,
    "shares_delta": 0,
    "followers_delta": 0
  }
]